eolymp/__init__.py
eolymp/acl/__init__.py
eolymp/acl/action_pb2.py
eolymp/acl/action_pb2.pyi
eolymp/acl/permission_service_http.py
eolymp/acl/permission_service_pb2.py
eolymp/acl/permission_service_pb2.pyi
eolymp/acl/policy_pb2.py
eolymp/acl/policy_pb2.pyi
eolymp/acl/policy_service_http.py
eolymp/acl/policy_service_pb2.py
eolymp/acl/policy_service_pb2.pyi
eolymp/annotations/__init__.py
eolymp/annotations/http_pb2.py
eolymp/annotations/http_pb2.pyi
eolymp/annotations/mcp_pb2.py
eolymp/annotations/mcp_pb2.pyi
eolymp/annotations/namespace_pb2.py
eolymp/annotations/namespace_pb2.pyi
eolymp/annotations/ratelimit_pb2.py
eolymp/annotations/ratelimit_pb2.pyi
eolymp/annotations/scope_pb2.py
eolymp/annotations/scope_pb2.pyi
eolymp/asset/__init__.py
eolymp/asset/asset_service_http.py
eolymp/asset/asset_service_pb2.py
eolymp/asset/asset_service_pb2.pyi
eolymp/atlas/__init__.py
eolymp/atlas/attachment_pb2.py
eolymp/atlas/attachment_pb2.pyi
eolymp/atlas/attachment_service_http.py
eolymp/atlas/attachment_service_pb2.py
eolymp/atlas/attachment_service_pb2.pyi
eolymp/atlas/bookmark_service_http.py
eolymp/atlas/bookmark_service_pb2.py
eolymp/atlas/bookmark_service_pb2.pyi
eolymp/atlas/code_template_pb2.py
eolymp/atlas/code_template_pb2.pyi
eolymp/atlas/code_template_service_http.py
eolymp/atlas/code_template_service_pb2.py
eolymp/atlas/code_template_service_pb2.pyi
eolymp/atlas/editor_service_http.py
eolymp/atlas/editor_service_pb2.py
eolymp/atlas/editor_service_pb2.pyi
eolymp/atlas/editorial_pb2.py
eolymp/atlas/editorial_pb2.pyi
eolymp/atlas/editorial_service_http.py
eolymp/atlas/editorial_service_pb2.py
eolymp/atlas/editorial_service_pb2.pyi
eolymp/atlas/form_pb2.py
eolymp/atlas/form_pb2.pyi
eolymp/atlas/problem_pb2.py
eolymp/atlas/problem_pb2.pyi
eolymp/atlas/problem_service_http.py
eolymp/atlas/problem_service_pb2.py
eolymp/atlas/problem_service_pb2.pyi
eolymp/atlas/scoring_score_pb2.py
eolymp/atlas/scoring_score_pb2.pyi
eolymp/atlas/scoring_service_http.py
eolymp-0.13.7.dist-info/METADATA
eolymp-0.13.7.dist-info/WHEEL
eolymp-0.13.7.dist-info/top_level.txt
eolymp-0.13.7.dist-info/RECORD
