Metadata-Version: 2.4
Name: eolymp
Version: 0.13.7
Summary: Eolymp SDK for Python
Home-page: https://github.com/eolymp/contracts
Author: Sergey Kolodyazhnyy
Author-email: sergey@eolymp.com
Classifier: Programming Language :: Python :: 3
Classifier: License :: OSI Approved :: MIT License
Classifier: Operating System :: OS Independent
Requires-Python: >=3.0
Dynamic: author
Dynamic: author-email
Dynamic: classifier
Dynamic: description
Dynamic: description-content-type
Dynamic: home-page
Dynamic: requires-python
Dynamic: summary
